docs/conf.py
flip/__init__.py
flip/_config.py
flip/utils.py
flip/covariance/__init__.py
flip/covariance/contraction.py
flip/covariance/cov_utils.py
flip/covariance/covariance.py
flip/covariance/fisher.py
flip/covariance/fit_utils.py
flip/covariance/fitter.py
flip/covariance/generator.py
flip/covariance/likelihood.py
flip/covariance/plot_utils.py
flip/covariance/symbolic.py
flip/covariance/analytical/__init__.py
flip/covariance/analytical/adamsblake17/__init__.py
flip/covariance/analytical/adamsblake17/coefficients.py
flip/covariance/analytical/adamsblake17/fisher_terms.py
flip/covariance/analytical/adamsblake17/flip_terms.py
flip/covariance/analytical/adamsblake17plane/__init__.py
flip/covariance/analytical/adamsblake17plane/coefficients.py
flip/covariance/analytical/adamsblake17plane/fisher_terms.py
flip/covariance/analytical/adamsblake17plane/flip_terms.py
flip/covariance/analytical/adamsblake17plane/generator.py
flip/covariance/analytical/adamsblake20/__init__.py
flip/covariance/analytical/adamsblake20/coefficients.py
flip/covariance/analytical/adamsblake20/fisher_terms.py
flip/covariance/analytical/adamsblake20/flip_terms.py
flip/covariance/analytical/carreres23/__init__.py
flip/covariance/analytical/carreres23/coefficients.py
flip/covariance/analytical/carreres23/fisher_terms.py
flip/covariance/analytical/carreres23/flip_terms.py
flip/covariance/analytical/carreres23/generator.py
flip/covariance/analytical/genericzdep/__init__.py
flip/covariance/analytical/genericzdep/coefficients.py
flip/covariance/analytical/genericzdep/flip_terms.py
flip/covariance/analytical/lai22/__init__.py
flip/covariance/analytical/lai22/coefficients.py
flip/covariance/analytical/lai22/fisher_terms.py
flip/covariance/analytical/lai22/flip_terms.py
flip/covariance/analytical/lai22/generator.py
flip/covariance/analytical/lai22/h_terms.py
flip/covariance/analytical/lai22/symbolic.py
flip/covariance/analytical/ravouxcarreres/__init__.py
flipcosmo-1.2.1.dist-info/licenses/LICENSE
flipcosmo-1.2.1.dist-info/METADATA
flipcosmo-1.2.1.dist-info/WHEEL
flipcosmo-1.2.1.dist-info/top_level.txt
flipcosmo-1.2.1.dist-info/RECORD
