Metadata-Version: 2.4
Name: flipcosmo
Version: 1.2.1
Summary:  Field Level Inference Package
Author-email: Corentin Ravoux <corentin.ravoux.research@gmail.com>, Bastien Carreres <bastien.carreres@duke.edu>
License-Expression: MIT
Requires-Python: >=3.10
License-File: LICENSE
Requires-Dist: pandas
Requires-Dist: numpy
Requires-Dist: scipy>=1.12
Requires-Dist: matplotlib
Requires-Dist: importlib-metadata
Requires-Dist: emcee
Requires-Dist: iminuit
Requires-Dist: astropy
Requires-Dist: mpmath
Provides-Extra: docs
Requires-Dist: markdown; extra == "docs"
Requires-Dist: sphinx>=5.2.3; extra == "docs"
Requires-Dist: sphinx-markdown-tables>=0.0.15; extra == "docs"
Requires-Dist: numpydoc; extra == "docs"
Requires-Dist: sphinx_book_theme; extra == "docs"
Requires-Dist: myst-parser; extra == "docs"
Requires-Dist: sphinx-copybutton; extra == "docs"
Requires-Dist: sphinx-design; extra == "docs"
Requires-Dist: sphinx-inline-tabs; extra == "docs"
Requires-Dist: sphinx-tabs; extra == "docs"
Requires-Dist: sphinx-autoapi; extra == "docs"
Dynamic: license-file
